{
  "version": "7",
  "dialect": "postgresql",
  "entries": [
    {
      "idx": 0,
      "version": "7",
      "when": 1775892107552,
      "tag": "0000_init",
      "breakpoints": true
    },
    {
      "idx": 1,
      "version": "7",
      "when": 1776537600000,
      "tag": "0001_taxonomy_rename",
      "breakpoints": true
    },
    {
      "idx": 2,
      "version": "7",
      "when": 1776613431034,
      "tag": "0002_wiki_types_based_on_version",
      "breakpoints": true
    },
    {
      "idx": 3,
      "version": "7",
      "when": 1776775199812,
      "tag": "0003_wikis_metadata_jsonb",
      "breakpoints": true
    },
    {
      "idx": 4,
      "version": "7",
      "when": 1777248000000,
      "tag": "0004_wikis_citation_declarations",
      "breakpoints": true
    },
    {
      "idx": 5,
      "version": "7",
      "when": 1777680000000,
      "tag": "0005_wikis_slug_partial_uidx",
      "breakpoints": true
    },
    {
      "idx": 6,
      "version": "7",
      "when": 1777766400000,
      "tag": "0006_fragments_embedding_retry",
      "breakpoints": true
    },
    {
      "idx": 7,
      "version": "7",
      "when": 1777852800000,
      "tag": "0007_wikis_add_description",
      "breakpoints": true
    },
    {
      "idx": 8,
      "version": "7",
      "when": 1777939200000,
      "tag": "0008_fragments_dedup_hash_partial_idx",
      "breakpoints": true
    },
    {
      "idx": 9,
      "version": "7",
      "when": 1778025600000,
      "tag": "0009_search_recall_tags_and_triggers",
      "breakpoints": true
    },
    {
      "idx": 10,
      "version": "7",
      "when": 1778112000000,
      "tag": "0010_backfill_zombie_edges",
      "breakpoints": true
    },
    {
      "idx": 11,
      "version": "7",
      "when": 1778198400000,
      "tag": "0011_wikis_add_structure",
      "breakpoints": true
    }
  ]
}
